mlkits/__init__.py
mlkits/config.py
mlkits/log.py
mlkits/cli/__init__.py
mlkits/cli/predict.py
mlkits/cli/train.py
mlkits/contrib/__init__.py
mlkits/contrib/model/__init__.py
mlkits/contrib/model/gbdt.py
mlkits/contrib/model/xgboost.py
mlkits/data/__init__.py
mlkits/data/ops.py
mlkits/data/dataset/__init__.py
mlkits/data/dataset/handler.py
mlkits/data/dataset/loader.py
mlkits/data/dataset/processor.py
mlkits/data/dataset/utils.py
mlkits/data/dataset/weight.py
mlkits/model/__init__.py
mlkits/model/base.py
mlkits/model/trainer.py
mlkits/model/interpret/__init__.py
mlkits/model/interpret/base.py
mlkits/utils/__init__.py
mlkits/utils/data.py
mlkits/utils/serial.py
mlkits-0.0.6.dist-info/LICENSE
mlkits-0.0.6.dist-info/METADATA
mlkits-0.0.6.dist-info/WHEEL
mlkits-0.0.6.dist-info/entry_points.txt
mlkits-0.0.6.dist-info/top_level.txt
mlkits-0.0.6.dist-info/RECORD
