Metadata-Version: 2.1
Name: mlkits
Version: 0.0.6
Summary: Common tools and training models for machine learning.
Home-page: https://gitee.com/winter1991/mlkits
Author: WangSihong
Author-email: wangsihong@live.com
License: MIT Licence
Keywords: mlkits,xgboost,lightgbm
Platform: UNKNOWN
Requires-Python: >=3.7.1
License-File: LICENSE
Requires-Dist: Cython (~=0.29.28)
Requires-Dist: dill (~=0.3.4)
Requires-Dist: lightgbm (~=3.3.2)
Requires-Dist: pandas (~=1.3.5)
Requires-Dist: PyYAML (~=6.0)
Requires-Dist: storage (~=0.0.4.3)
Requires-Dist: tqdm (~=4.63.0)
Requires-Dist: typing-extensions (~=4.4.0)
